bibchex/__init__.py
bibchex/__main__.py
bibchex/asyncrate.py
bibchex/checker.py
bibchex/config.py
bibchex/data.py
bibchex/differ.py
bibchex/problems.py
bibchex/strutil.py
bibchex/ui.py
bibchex/util.py
bibchex/checks/__init__.py
bibchex/checks/authors.py
bibchex/checks/basic.py
bibchex/checks/common.py
bibchex/checks/isbn.py
bibchex/checks/publication.py
bibchex/checks/title.py
bibchex/data/default_config.json
bibchex/data/default_config.json~
bibchex/data/output.html
bibchex/output/__init__.py
bibchex/output/common_output.py
bibchex/output/html.py
bibchex/sources/__init__.py
bibchex/sources/crossref.py
bibchex/sources/datacite.py
bibchex/sources/isbn.py
bibchex/sources/meta.py
bibchex-0.1.6.dist-info/METADATA
bibchex-0.1.6.dist-info/WHEEL
bibchex-0.1.6.dist-info/entry_points.txt
bibchex-0.1.6.dist-info/top_level.txt
bibchex-0.1.6.dist-info/RECORD
