Metadata-Version: 2.1
Name: bibchex
Version: 0.1.6
Summary: Check your BibTeX files for consistency and sanity.
Home-page: http://github.com/tinloaf/bibchex/
Author: Lukas Barth
Author-email: pypi@mbox.tinloaf.de
License: UNKNOWN
Project-URL: Bug Tracker, https://github.com/tinloaf/bibchex/issues
Project-URL: Documentation, https://tinloaf.github.io/bibchex/
Keywords: bibtex latex bibliography
Platform: UNKNOWN
Classifier: License :: OSI Approved :: MIT License
Requires-Python: >=3.6
Requires-Dist: aiohttp (>=3.6.2)
Requires-Dist: bibtexparser (>=1.1.0)
Requires-Dist: crossref-commons-reverse (>=0.0.7.1)
Requires-Dist: fuzzywuzzy (>=0.18.0)
Requires-Dist: isbnlib (>=3.10.3)
Requires-Dist: Jinja2 (>=2.11.1)
Requires-Dist: nameparser (>=1.0.6)
Requires-Dist: python-dateutil (>=2.8.1)
Requires-Dist: ratelimit (>=2.2.1)
Requires-Dist: python-Levenshtein (>=0.12.0)
